test_graphs/__init__.py
test_graphs/test_calculations.py
tgcnn_act_graph/__init__.py
tgcnn_act_graph/calculations.py
tgcnn_act_graph/figures.py
tgcnn_act_graph/max_act_diff.py
tgcnn_act_graph/utils.py
tgcnn_act_graph-0.3.1.dist-info/LICENSE.txt
tgcnn_act_graph-0.3.1.dist-info/METADATA
tgcnn_act_graph-0.3.1.dist-info/WHEEL
tgcnn_act_graph-0.3.1.dist-info/top_level.txt
tgcnn_act_graph-0.3.1.dist-info/RECORD
