Metadata-Version: 2.1
Name: tgcnn_act_graph
Version: 0.3.1
License-File: LICENSE.txt
Requires-Dist: networkx
Requires-Dist: pandas
Requires-Dist: matplotlib
Requires-Dist: numpy
Requires-Dist: pytest
